prompt_enhance_service/__init__.py
prompt_enhance_service/prompt_enhancer.py
prompt_enhance_service/database_layer/__init__.py
prompt_enhance_service/database_layer/database_connection.py
prompt_enhance_service/database_layer/google_firestore.py
prompt_enhance_service/schemas/__init__.py
prompt_enhance_service/schemas/domain_questions.py
prompt_enhance_service/schemas/prompt_request.py
prompt_enhance_service/services/__init__.py
prompt_enhance_service/services/prompt_enhancer_dynamic.py
prompt_enhance_service/services/prompt_enhancer_static.py
prompt_enhance_service-0.1.4.dist-info/LICENSE
prompt_enhance_service-0.1.4.dist-info/METADATA
prompt_enhance_service-0.1.4.dist-info/WHEEL
prompt_enhance_service-0.1.4.dist-info/top_level.txt
prompt_enhance_service-0.1.4.dist-info/RECORD
