Metadata-Version: 2.1
Name: prompt_enhance_service
Version: 0.1.4
Summary: A brief description of your package
Author: Jinka Sai Jagadeesh
Author-email: saijagadeesh.jinka@gavstech.com
License: GAVS Proprietary License
Classifier: Programming Language :: Python :: 3
Classifier: License :: OSI Approved :: MIT License
Classifier: Operating System :: OS Independent
Requires-Python: >=3.12
License-File: LICENSE
Requires-Dist: python-dotenv
Requires-Dist: google-cloud-firestore
